pg2s/__init__.py
pg2s/metric.py
py_pg2s-0.1.0.dist-info/LICENSE
py_pg2s-0.1.0.dist-info/METADATA
py_pg2s-0.1.0.dist-info/WHEEL
py_pg2s-0.1.0.dist-info/top_level.txt
py_pg2s-0.1.0.dist-info/RECORD
