Metadata-Version: 2.1
Name: py-pg2s
Version: 0.1.0
Summary: pg2s metric implementation
Author-email: Michele Brienza <brienza@diag.uniroma1.it>, Francesco Argenziano <argenziano@diag.uniroma1.it>
Project-URL: Homepage, https://lab-rococo-sapienza.github.io/map-vlm/
Classifier: Programming Language :: Python :: 3
Classifier: License :: OSI Approved :: Apache Software License
Classifier: Operating System :: OS Independent
Requires-Python: >=3.9
License-File: LICENSE
Requires-Dist: numpy ==1.26.4
Requires-Dist: sentence-transformers ==3.1.1
Requires-Dist: gensim ==4.3.3
Requires-Dist: spacy ==3.7.5
